mpoints/__init__.py
mpoints/hybrid_hawkes_exp.py
mpoints/hybrid_hawkes_exp_cython.cpython-36m-darwin.so
mpoints/plot_tools.py
mpoints/setup.py
mpoints-0.2.dist-info/METADATA
mpoints-0.2.dist-info/RECORD
mpoints-0.2.dist-info/WHEEL
mpoints-0.2.dist-info/top_level.txt
