Metadata-Version: 2.1
Name: mpoints
Version: 0.2
Summary: Simulate and estimate state-dependent Hawkes processes.
Home-page: https://mpoints.readthedocs.io
Author: Maxime Morariu-Patrichi, Mikko Pakkanen
Author-email: maximemorariu@me.com
License: UNKNOWN
Platform: UNKNOWN
Classifier: Programming Language :: Python :: 3
Classifier: License :: OSI Approved :: MIT License
Classifier: Operating System :: OS Independent
